.gitignore
.travis.yml
MANIFEST.in
README.rst
setup.py
validation-files.yaml
validation-options.yaml
demo/README.rst
demo/demo.py
demo/foobar.css
demo/moomodule.py
demo/validation-files.yaml
demo/validation-options.yaml
docs/CHANGES.rst
docs/Makefile
docs/presentations/Python Helsinki meet-up May.key
docs/presentations/Python Helsinki meet-up May.pdf
docs/source/community.rst
docs/source/conf.py
docs/source/configuration.rst
docs/source/develop.rst
docs/source/guidelines.rst
docs/source/index.rst
docs/source/installation.rst
docs/source/integration.rst
docs/source/prerequisites.rst
docs/source/validators.rst
docs/source/images/globals.png
docs/source/tools/addjsglobals.rst
docs/source/tools/expandtabs.rst
docs/source/tools/ghetto.rst
docs/source/tools/index.rst
ghettoci/__init__.py
ghettoci/main.py
scripts/publish-docs.sh
tests/test_add_js_globals.py
tests/test_ghetto.py
tests/test_validators.py
tests/validators/css/simple-fail/tests.css
tests/validators/css/simple-pass/test.css
tests/validators/evilspace/simple-fail/test.txt
tests/validators/generic/empty-files-pass/test.txt
tests/validators/generic/empty-files-pass/validation-options.yaml
tests/validators/javascript/options-pass/README.txt
tests/validators/javascript/options-pass/test.js
tests/validators/javascript/options-pass/validation-options.yaml
tests/validators/javascript/simple-fail/test.js
tests/validators/javascript/simple-fail/validator-options.yaml
tests/validators/javascript/simple-pass/test.js
tests/validators/javascript/strict-fail/test.js
tests/validators/python/pdb-fail/test.py
tests/validators/python/pdb-pass/test.py
tests/validators/python/simple-fail/test.py
tests/validators/python/simple-pass/test.py
tests/validators/python/simple-pass-py2/test.py
tests/validators/python/simple-pass-py3k/test.py
tests/validators/python/simple-pass-py3k/validation-options.yaml
tests/validators/rst/rst-fail/test.rst
tests/validators/rst/rst-import-pass/file.rst
tests/validators/rst/rst-import-pass/test.rst
vvv.egg-info/PKG-INFO
vvv.egg-info/SOURCES.txt
vvv.egg-info/dependency_links.txt
vvv.egg-info/entry_points.txt
vvv.egg-info/not-zip-safe
vvv.egg-info/requires.txt
vvv.egg-info/top_level.txt
