Metadata-Version: 1.1
Name: vvv
Version: 0.4.3
Summary: A convenience utility for software source code validation and linting
Home-page: https://github.com/miohtama/vvv
Author: Mikko Ohtamaa
Author-email: mikko@opensourcehacker.com
License: GPL3+
Platform: UNKNOWN
Classifier: Programming Language :: Python
